datasette_export_notebook/__init__.py
datasette_export_notebook/utils.py
datasette_export_notebook/templates/export_notebook.html
datasette_export_notebook-1.0.1.dist-info/METADATA
datasette_export_notebook-1.0.1.dist-info/WHEEL
datasette_export_notebook-1.0.1.dist-info/entry_points.txt
datasette_export_notebook-1.0.1.dist-info/top_level.txt
datasette_export_notebook-1.0.1.dist-info/RECORD
