Metadata-Version: 2.1
Name: datasette-export-notebook
Version: 1.0.1
Summary: Datasette plugin providing instructions for exporting data to Jupyter or Observable
Home-page: https://github.com/simonw/datasette-export-notebook
Author: Simon Willison
License: Apache License, Version 2.0
Project-URL: Issues, https://github.com/simonw/datasette-export-notebook/issues
Project-URL: CI, https://github.com/simonw/datasette-export-notebook/actions
Project-URL: Changelog, https://github.com/simonw/datasette-export-notebook/releases
Requires-Python: >=3.6
Requires-Dist: datasette
Provides-Extra: test
Requires-Dist: pytest ; extra == 'test'
Requires-Dist: pytest-asyncio ; extra == 'test'
Requires-Dist: sqlite-utils ; extra == 'test'
